LICENSE
README.md
setup.py
getchlib/__init__.py
getchlib/ctrl.py
getchlib/decorators.py
getchlib/getkey.py
getchlib/hotkey.py
getchlib/pressed.py
getchlib/printer.py
getchlib/term.py
getchlib/unix.py
getchlib/windows.py
getchlib.egg-info/PKG-INFO
getchlib.egg-info/SOURCES.txt
getchlib.egg-info/dependency_links.txt
getchlib.egg-info/top_level.txt